airbus/__init__.py
airbus/__main__.py
airbus/yuque.cfg
airbus/cli/__init__.py
airbus/cli/cli_parser.py
airbus/cli/commands/__init__.py
airbus/cli/commands/yuque.py
airbus/db/__init__.py
airbus/db/_impala.py
airbus/decorators/__init__.py
airbus/decorators/_progressbar.py
airbus/decorators/_retry.py
airbus/decorators/_timeit.py
airbus/robots/__init__.py
airbus/robots/_webcom.py
airbus/utils/__init__.py
airbus/utils/helpers.py
airbus/utils/model_loading.py
airbus-0.0.8.dist-info/LICENSE
airbus-0.0.8.dist-info/METADATA
airbus-0.0.8.dist-info/WHEEL
airbus-0.0.8.dist-info/entry_points.txt
airbus-0.0.8.dist-info/top_level.txt
airbus-0.0.8.dist-info/RECORD
